{"reg": {"lineas": [{"total": 4.0, "text": "Finger pollo", "cant": 2, "des": "  2 Finger pollo", "precio": 2.0}, {"total": 7.9, "text": "Jamon", "cant": 1, "des": "  1 Jamon Familiar Sola", "precio": 7.9}, {"total": 6.2, "text": "Jamon y champi", "cant": 1, "des": "  1 Jamon y champi Mediana Sola", "precio": 6.2}, {"total": 6.0, "text": "Refresco", "cant": 4, "des": "  4 Refresco", "precio": 1.5}], "numTicket": "170330213713", "para_llevar": "Para tomar", "fecha": "30/03/2017_21:37:13", "num_tlf": "", "modo_pago": "Efectivo", "total": 24.1, "num_avisador": "5"}}