{"reg": {"lineas": [{"total": 7.5, "text": "Pizza con", "cant": 1, "des": "  1 Pizza con Jamon york Pollo Pi\u00f1a Champin Mediana Sola roqueforr", "precio": 7.5}, {"total": 1.5, "text": "Finger queso", "cant": 1, "des": "  1 Finger queso", "precio": 1.5}, {"total": 2.0, "text": "Finger pollo", "cant": 1, "des": "  1 Finger pollo", "precio": 2.0}], "numTicket": "170330231824", "para_llevar": "Domicilio", "fecha": "30/03/2017_23:18:24", "num_tlf": "665049302", "modo_pago": "Efectivo", "total": 11.0, "num_avisador": "Domicilio"}}