{"reg": {"lineas": [{"total": 7.45, "text": "Pizza infantil", "cant": 1, "des": "  1 Pizza infantil in tomate la pizza ", "precio": 7.45}, {"total": 5.95, "text": "Finger infantil", "cant": 1, "des": "  1 Finger infantil", "precio": 5.95}, {"total": 6.5, "text": "Carbonara", "cant": 1, "des": "  1 Carbonara Mediana Sola", "precio": 6.5}, {"total": 0.0, "text": "Jamon y champi", "cant": 1, "des": "  1 Jamon y champi Mediana Sola", "precio": 0.0}, {"total": 3.0, "text": "Cerveza", "cant": 2, "des": "  2 Cerveza", "precio": 1.5}], "numTicket": "170318135616", "para_llevar": "Para tomar", "fecha": "18/03/2017_13:56:16", "num_tlf": "", "modo_pago": "Efectivo", "total": 22.9, "num_avisador": "4"}}