{"reg": {"lineas": [{"total": 0.0, "text": "Carbonara", "cant": 1, "des": "  1 Carbonara Mediana Sola", "precio": 0.0}, {"total": 9.0, "text": "Pizza con", "cant": 1, "des": "  1 Pizza con Jamon york Pollo Huevo Familiar Sola", "precio": 9.0}, {"total": 1.5, "text": "Alitas de pollo", "cant": 1, "des": "  1 Alitas de pollo", "precio": 1.5}], "numTicket": "170223215235", "para_llevar": "Domicilio", "fecha": "23/02/2017_21:52:35", "num_tlf": "661142521", "modo_pago": "Efectivo", "total": 10.5, "num_avisador": "Domicilio"}}