{"reg": {"lista_ticket": ["db/pd/2017_04_23_21_27_071.22.json", "db/pd/2017_04_23_21_58_541.22.json", "db/pd/2017_04_23_23_11_061.22.json", "db/pd/2017_04_23_20_13_341.22.json", "db/pd/2017_04_23_22_24_541.22.json", "db/pd/2017_04_23_21_30_091.22.json", "db/pd/2017_04_23_21_41_511.22.json", "db/pd/2017_04_23_20_45_461.22.json", "db/pd/2017_04_23_21_43_381.22.json", "db/pd/2017_04_23_20_49_511.22.json", "db/pd/2017_04_23_23_49_471.22.json", "db/pd/2017_04_23_22_40_291.22.json", "db/pd/2017_04_23_22_27_151.22.json", "db/pd/2017_04_23_21_56_051.22.json", "db/pd/2017_04_23_22_51_371.22.json", "db/pd/2017_04_23_21_28_141.22.json", "db/pd/2017_04_23_21_33_221.22.json", "db/pd/2017_04_23_20_24_361.22.json", "db/pd/2017_04_23_20_52_291.22.json", "db/pd/2017_04_23_22_05_001.22.json", "db/pd/2017_04_23_21_35_111.22.json", "db/pd/2017_04_23_22_09_521.22.json", "db/pd/2017_04_23_20_53_301.22.json", "db/pd/2017_04_23_22_06_221.22.json", "db/pd/2017_04_23_21_47_111.22.json", "db/pd/2017_04_23_23_01_471.22.json", "db/pd/2017_04_23_21_04_471.22.json", "db/pd/2017_04_23_21_31_421.22.json", "db/pd/2017_04_23_22_21_381.22.json", "db/pd/2017_04_23_23_08_411.22.json", "db/pd/2017_04_23_21_28_531.22.json", "db/pd/2017_04_23_21_37_521.22.json", "db/pd/2017_04_23_22_34_081.22.json", "db/pd/2017_04_23_22_50_191.22.json", "db/pd/2017_04_23_20_43_161.22.json", "db/pd/2017_04_23_20_46_401.22.json", "db/pd/2017_04_23_21_05_481.22.json", "db/pd/2017_04_23_22_23_041.22.json", "db/pd/2017_04_23_23_12_111.22.json", "db/pd/2017_04_23_23_09_561.22.json", "db/pd/2017_04_23_20_57_201.22.json", "db/pd/2017_04_23_21_40_461.22.json", "db/pd/2017_04_23_21_09_561.22.json", "db/pd/2017_04_23_21_52_171.22.json", "db/pd/2017_04_23_22_16_031.22.json", "db/pd/2017_04_23_21_21_091.22.json", "db/pd/2017_04_23_21_08_551.22.json", "db/pd/2017_04_23_20_19_301.22.json", "db/pd/2017_04_23_23_21_031.22.json"], "fecha": "24/04/2017_00:15:06", "caja_dia": 585.7999999999997, "total_gastos": 0.0, "targeta": 49.4, "lista_conteo": [{"total": 150.0, "can": "3", "tipo": 50.0, "texto_tipo": "Billetes"}, {"total": 200.0, "can": "10", "tipo": 20.0, "texto_tipo": "Billetes"}, {"total": 230.0, "can": "23", "tipo": 10.0, "texto_tipo": "Billetes"}, {"total": 85.0, "can": "17", "tipo": 5.0, "texto_tipo": "Billetes"}, {"total": 4.0, "can": "2", "tipo": 2.0, "texto_tipo": "Monedas"}, {"total": 22.0, "can": "22", "tipo": 1.0, "texto_tipo": "Monedas"}, {"total": 14.5, "can": "29", "tipo": 0.5, "texto_tipo": "Monedas"}, {"total": 0.8, "can": "4", "tipo": 0.2, "texto_tipo": "Monedas"}, {"total": 3.0, "can": "30", "tipo": 0.1, "texto_tipo": "Monedas"}, {"total": 1.0, "can": "20", "tipo": 0.05, "texto_tipo": "Monedas"}, {"total": 0.04, "can": "2", "tipo": 0.02, "texto_tipo": "Monedas"}, {"total": 0.01, "can": "1", "tipo": 0.01, "texto_tipo": "Monedas"}, {"total": 0.0, "can": "", "tipo": 0.0, "texto_tipo": "Monedas"}], "cambio": "200", "lista_gastos": [], "efectivo": 510.3499999999999, "descuadre": 26.04999999999984}}